setup.cfg
setup.py
pg_channels/__init__.py
pg_channels.egg-info/PKG-INFO
pg_channels.egg-info/SOURCES.txt
pg_channels.egg-info/dependency_links.txt
pg_channels.egg-info/requires.txt
pg_channels.egg-info/top_level.txt