Metadata-Version: 1.1
Name: pg-channels
Version: 1.0
Summary: Python wrapper for PostgreSQL NOTIFY and LISTEN commands.
Home-page: https://github.com/nickdmoore/pg_channels
Author: Nick Moore
Author-email: nickdmoore@gmail.com
License: MIT
Download-URL: https://github.com/nickdmoore/pg_channels/archive/1.0.tar.gz
Keywords: PostgreSQL,NOTIFY,LISTEN,channels
Platform: UNKNOWN
Classifier: Programming Language :: Python
Classifier: Programming Language :: Python :: 3.6
